{
  "byFish": [
    "Aal",
    "Bachforelle",
    "Bachsaibling",
    "Barbe",
    "Bitterling",
    "Blaufelchen",
    "Brachse",
    "Edelkrebs",
    "Elritze",
    "Flussbarsch",
    "Frauennerfling",
    "Giebel",
    "Goldorfe",
    "Grundeln",
    "Gründling",
    "Güster",
    "Hasel",
    "Hecht",
    "Huchen",
    "Kamberkrebs",
    "Karausche",
    "Karpfen",
    "Kaulbarsch",
    "Lachs",
    "Laube",
    "Mairenke",
    "Moderlieschen",
    "Mühlkoppe",
    "Nase",
    "Nerfling",
    "Neunauge",
    "Perlfisch",
    "Regenbogenforelle",
    "Renke",
    "Rotauge",
    "Rotfeder",
    "Rutte",
    "Schied",
    "Schlammpeitzger",
    "Schleie",
    "Schneider",
    "Schrätzer",
    "Seeforelle",
    "Seesaibling",
    "Steinbeißer",
    "Steinkrebs",
    "Sterlet",
    "Stichling",
    "Streber",
    "Strömer",
    "Stör",
    "Waller",
    "Zander",
    "Zingel",
    "Zobel",
    "Zope",
    "Zwergwels",
    "Zährte",
    "Äsche"
  ],
  "generalCount": 77,
  "report": {
    "generalCount": 77,
    "byFish": {
      "Waller": 33,
      "Aal": 31,
      "Rutte": 29,
      "Bachforelle": 27,
      "Zander": 26,
      "Hecht": 22,
      "Äsche": 20,
      "Karpfen": 20,
      "Flussbarsch": 19,
      "Barbe": 18,
      "Schied": 16,
      "Blaufelchen": 16,
      "Brachse": 15,
      "Huchen": 15,
      "Mühlkoppe": 15,
      "Schleie": 15,
      "Neunauge": 12,
      "Schrätzer": 11,
      "Stichling": 11,
      "Rotauge": 11,
      "Streber": 10,
      "Nase": 10,
      "Zingel": 9,
      "Bachsaibling": 9,
      "Seesaibling": 9,
      "Rotfeder": 8,
      "Regenbogenforelle": 8,
      "Gründling": 7,
      "Schlammpeitzger": 7,
      "Hasel": 7,
      "Güster": 7,
      "Kaulbarsch": 6,
      "Renke": 6,
      "Elritze": 6,
      "Karausche": 6,
      "Edelkrebs": 6,
      "Lachs": 5,
      "Moderlieschen": 5,
      "Nerfling": 5,
      "Bitterling": 5,
      "Grundeln": 5,
      "Perlfisch": 4,
      "Steinbeißer": 4,
      "Sterlet": 4,
      "Strömer": 4,
      "Zährte": 4,
      "Zope": 4,
      "Seeforelle": 4,
      "Mairenke": 4,
      "Schneider": 4,
      "Steinkrebs": 4,
      "Frauennerfling": 3,
      "Laube": 3,
      "Giebel": 3,
      "Zwergwels": 3,
      "Stör": 3,
      "Zobel": 3,
      "Goldorfe": 1,
      "Kamberkrebs": 1
    },
    "generalSample": [
      {
        "number": "1.003",
        "question": "Zu welcher Gruppe der Wirbeltiere gehören die meisten einheimischen Süßwasserfischarten?"
      },
      {
        "number": "1.008",
        "question": "Welches Merkmal wird zur Artbestimmung bei den karpfenartigen Fischen (Cypriniden) herangezogen?"
      },
      {
        "number": "1.014",
        "question": "Wie hat man sich die Urform des Karpfens vorzustellen?"
      }
    ]
  }
}